<?xml version="1.0" encoding="UTF-8"?>

<odoo>
    <record id="stock_picking_tree"
        model="ir.ui.view">
        <field name="name">stock.picking.tree.week</field>
        <field name="model">stock.picking</field>
        <field name="inherit_id" ref="stock.view_move_picking_tree"/>
        <field name="arch" type="xml">
            <xpath expr="//field[@name='partner_id']" position="before">
                <field name="week_of_shipment"/>
            </xpath>
        </field>
    </record>

</odoo>
